{
  "levelBonuses": {
    "health": 8,
    "attack": 1,
    "speed": 5
  },
  "weapon": "Shoes",
  "name": "Christina K.",
  "id": "CK",
  "sprite": "CK",
  "health": 65,
  "defense": 0,
  "speed": 160,
  "abilities": [
    {
      "name": "Shoe Throwing",
      "type": "AttackSkillshot",
      "icon": "Icon - Shoe Throwing.png",
      "description": "Fire a shoe at a single target.",
      "dmgBase": "3",
      "dmgRatio": "1",
      "range": 2000,
      "cd": 10,
      "stand": 8,
      "speed": 30,
      "width": 50
    },
    {
      "name": "Order UP!",
      "type": "AttackPoint",
      "icon": "Icon - Coffee Boost.png",
      "description": "Launch a coffee cup-missile at a point on the ground.",
      "dmgBase": "15",
      "dmgRatio": "",
      "range": 250,
      "cd": 20,
      "stand": 24,
      "radius": 48
    }
  ]
}